woo_commerce_sdk-1.0.0.dist-info/licenses/LICENSE
woocommercerestapi/__init__.py
woocommercerestapi/api_helper.py
woocommercerestapi/configuration.py
woocommercerestapi/woocommercerestapi_client.py
woocommercerestapi/controllers/__init__.py
woocommercerestapi/controllers/attribute_id_terms_controller.py
woocommercerestapi/controllers/attributes_controller.py
woocommercerestapi/controllers/base_controller.py
woocommercerestapi/controllers/batch_controller.py
woocommercerestapi/controllers/categories_controller.py
woocommercerestapi/controllers/classes_controller.py
woocommercerestapi/controllers/continents_controller.py
woocommercerestapi/controllers/countries_controller.py
woocommercerestapi/controllers/coupons_controller.py
woocommercerestapi/controllers/currencies_controller.py
woocommercerestapi/controllers/customers_controller.py
woocommercerestapi/controllers/data_controller.py
woocommercerestapi/controllers/group_id_controller.py
woocommercerestapi/controllers/id_controller.py
woocommercerestapi/controllers/instance_id_controller.py
woocommercerestapi/controllers/locations_controller.py
woocommercerestapi/controllers/notes_controller.py
woocommercerestapi/controllers/orders_controller.py
woocommercerestapi/controllers/payment_gateways_controller.py
woocommercerestapi/controllers/product_id_variations_controller.py
woocommercerestapi/controllers/products_controller.py
woocommercerestapi/controllers/refunds_controller.py
woocommercerestapi/controllers/reports_controller.py
woocommercerestapi/controllers/reviews_controller.py
woocommercerestapi/controllers/settings_controller.py
woocommercerestapi/controllers/shipping_classes_controller.py
woocommercerestapi/controllers/shipping_methods_controller.py
woocommercerestapi/controllers/shipping_zones_controller.py
woocommercerestapi/controllers/system_status_controller.py
woocommercerestapi/controllers/tags_controller.py
woocommercerestapi/controllers/taxes_controller.py
woocommercerestapi/controllers/tools_controller.py
woo_commerce_sdk-1.0.0.dist-info/METADATA
woo_commerce_sdk-1.0.0.dist-info/WHEEL
woo_commerce_sdk-1.0.0.dist-info/top_level.txt
woo_commerce_sdk-1.0.0.dist-info/RECORD
